pytesstrain/__init__.py
pytesstrain/ambigs/__init__.py
pytesstrain/ambigs/extract.py
pytesstrain/ambigs/properties.py
pytesstrain/cli/__init__.py
pytesstrain/cli/collect_ambiguities.py
pytesstrain/cli/create_dictdata.py
pytesstrain/cli/create_ground_truth.py
pytesstrain/cli/json2unicharambigs.py
pytesstrain/cli/language_metrics.py
pytesstrain/cli/rewrap.py
pytesstrain/metrics/__init__.py
pytesstrain/metrics/cer.py
pytesstrain/metrics/metrics.py
pytesstrain/metrics/wer.py
pytesstrain/tesseract/__init__.py
pytesstrain/text2image/__init__.py
pytesstrain/text2image/pytext2image.py
pytesstrain/train/__init__.py
pytesstrain/train/run_test.py
pytesstrain/train/run_tests.py
pytesstrain/utils/__init__.py
pytesstrain/utils/chdir.py
pytesstrain/utils/fontsdir.py
pytesstrain/utils/setuppath.py
pytesstrain/utils/wordlist.py
pytesstrain/utils/wordsequence.py
pytesstrain-0.1.16.dist-info/LICENSE
pytesstrain-0.1.16.dist-info/METADATA
pytesstrain-0.1.16.dist-info/WHEEL
pytesstrain-0.1.16.dist-info/entry_points.txt
pytesstrain-0.1.16.dist-info/top_level.txt
pytesstrain-0.1.16.dist-info/RECORD
