Metadata-Version: 2.1
Name: pytesstrain
Version: 0.1.16
Summary: Collection of utilities for Tesseract OCR training
Home-page: https://github.com/wincentbalin/pytesstrain
Author: Wincent Balin
Author-email: wincent.balin+pytesstrain@gmail.com
License: Apache License (2.0)
Keywords: Tesseract,OCR,training
Platform: UNKNOWN
Classifier: Development Status :: 3 - Alpha
Classifier: Topic :: Text Processing
Classifier: Environment :: Console
Classifier: License :: OSI Approved :: Apache Software License
Classifier: Operating System :: OS Independent
Classifier: Programming Language :: Python
Classifier: Programming Language :: Python :: 3
Classifier: Programming Language :: Python :: 3.5
Classifier: Programming Language :: Python :: 3.6
Classifier: Programming Language :: Python :: 3.7
Classifier: Programming Language :: Python :: 3.8
Classifier: Programming Language :: Python :: 3.9
Classifier: Programming Language :: Python :: 3.10
License-File: LICENSE
Requires-Dist: pytesseract
Requires-Dist: editdistance
